goldretriever/.well-known/ai-plugin.json
goldretriever/.well-known/default-ai-plugin.json
goldretriever/.well-known/logo.png
goldretriever/.well-known/openapi.yaml
goldretriever/__init__.py
goldretriever/config.yml
goldretriever/datastore/__init__.py
goldretriever/datastore/datastore.py
goldretriever/datastore/executor/Dockerfile
goldretriever/datastore/executor/__init__.py
goldretriever/datastore/executor/config.yml
goldretriever/datastore/executor/docarray_v1.py
goldretriever/datastore/factory.py
goldretriever/flow.yml
goldretriever/gateway.py
goldretriever/models/__init__.py
goldretriever/models/api.py
goldretriever/models/models.py
goldretriever/retriever.py
goldretriever/scripts/__init__.py
goldretriever/scripts/process_json/README.md
goldretriever/scripts/process_json/__init__.py
goldretriever/scripts/process_json/example.json
goldretriever/scripts/process_json/process_json.py
goldretriever/scripts/process_jsonl/README.md
goldretriever/scripts/process_jsonl/__init__.py
goldretriever/scripts/process_jsonl/example.jsonl
goldretriever/scripts/process_jsonl/process_jsonl.py
goldretriever/scripts/process_zip/README.md
goldretriever/scripts/process_zip/__init__.py
goldretriever/scripts/process_zip/example.zip
goldretriever/scripts/process_zip/process_zip.py
goldretriever/services/__init__.py
goldretriever/services/chunks.py
goldretriever/services/date.py
goldretriever/services/extract_metadata.py
goldretriever/services/file.py
goldretriever/services/openai.py
goldretriever/services/pii_detection.py
goldretriever-0.1.5.dist-info/LICENSE
goldretriever-0.1.5.dist-info/METADATA
goldretriever-0.1.5.dist-info/WHEEL
goldretriever-0.1.5.dist-info/entry_points.txt
goldretriever-0.1.5.dist-info/RECORD
