Metadata-Version: 2.1
Name: goldretriever
Version: 0.1.5
Summary: Create and host retrieval plugins for ChatGPT in one click
Author: Jina AI
Author-email: hello@jina.ai
Requires-Python: >=3.8,<4.0
Classifier: Programming Language :: Python :: 3
Classifier: Programming Language :: Python :: 3.8
Classifier: Programming Language :: Python :: 3.9
Classifier: Programming Language :: Python :: 3.10
Classifier: Programming Language :: Python :: 3.11
Requires-Dist: PyPDF2 (>=3.0.1,<4.0.0)
Requires-Dist: arrow (>=1.2.3,<2.0.0)
Requires-Dist: docarray (>=0.21.0,<0.22.0)
Requires-Dist: docx2txt (>=0.8,<0.9)
Requires-Dist: fastapi (>=0.92.0,<0.93.0)
Requires-Dist: jcloud (>=0.2.10,<0.3.0)
Requires-Dist: jina (>=3.16.0,<4.0.0)
Requires-Dist: numpy (>=1.24.2,<2.0.0)
Requires-Dist: openai (>=0.27.2,<0.28.0)
Requires-Dist: pydantic (>=1.10.5,<2.0.0)
Requires-Dist: pyjwt (==2.6.0)
Requires-Dist: python-dotenv (>=0.21.1,<0.22.0)
Requires-Dist: python-multipart (>=0.0.6,<0.0.7)
Requires-Dist: python-pptx (>=0.6.21,<0.7.0)
Requires-Dist: requests (>=2.27.1,<3.0.0)
Requires-Dist: tenacity (>=8.2.1,<9.0.0)
Requires-Dist: tiktoken (>=0.3.1,<0.4.0)
Requires-Dist: typer (>=0.7.0,<0.8.0)
Requires-Dist: urllib3 (>=1.26.7,<2.0.0)
Requires-Dist: uvicorn (>=0.20.0,<0.21.0)
Requires-Dist: wheel (>=0.37.0,<0.38.0)
